CHANGES.rst
DESCRIPTION.rst
LICENSE
MANIFEST.in
README.md
setup.py
src/wai.annotations.vgg.egg-info/PKG-INFO
src/wai.annotations.vgg.egg-info/SOURCES.txt
src/wai.annotations.vgg.egg-info/dependency_links.txt
src/wai.annotations.vgg.egg-info/entry_points.txt
src/wai.annotations.vgg.egg-info/namespace_packages.txt
src/wai.annotations.vgg.egg-info/requires.txt
src/wai.annotations.vgg.egg-info/top_level.txt
src/wai/annotations/vgg/__init__.py
src/wai/annotations/vgg/component/_FromVGG.py
src/wai/annotations/vgg/component/_ToVGG.py
src/wai/annotations/vgg/component/_VGGReader.py
src/wai/annotations/vgg/component/_VGGWriter.py
src/wai/annotations/vgg/component/__init__.py
src/wai/annotations/vgg/configuration/_FileAttributes.py
src/wai/annotations/vgg/configuration/_Image.py
src/wai/annotations/vgg/configuration/_ImageQuality.py
src/wai/annotations/vgg/configuration/_PolygonShapeAttributes.py
src/wai/annotations/vgg/configuration/_RectShapeAttributes.py
src/wai/annotations/vgg/configuration/_Region.py
src/wai/annotations/vgg/configuration/_RegionAttributes.py
src/wai/annotations/vgg/configuration/_VGGFile.py
src/wai/annotations/vgg/configuration/__init__.py
src/wai/annotations/vgg/specifier/_VGGInputFormatSpecifier.py
src/wai/annotations/vgg/specifier/_VGGOutputFormatSpecifier.py
src/wai/annotations/vgg/specifier/__init__.py
src/wai/annotations/vgg/utils/__init__.py
src/wai/annotations/vgg/utils/_format.py
src/wai/annotations/vgg/utils/_shape_attributes.py